{
  "productName": "Windows Port Viewer",
  "version": "0.1.0",
  "identifier": "com.windows-port-viewer.app",
  "build": {
    "beforeDevCommand": "npm run dev",
    "beforeBuildCommand": "npm run generate",
    "devUrl": "http://localhost:1420",
    "frontendDist": "dist"
  },
  "app": {
    "windows": [
      {
        "title": "Windows Port Viewer",
        "width": 1400,
        "height": 900,
        "minWidth": 800,
        "minHeight": 600,
        "resizable": true,
        "maximizable": true,
        "minimizable": true,
        "closable": true,
        "center": true
      }
    ],
    "security": {
      "csp": null
    }
  },
  "bundle": {
    "active": false
  }
}
